[
    {
        "id": "24c04c71",
        "productId": "3503cf9d",
        "productName": "Revel",
        "bestFor": [
            "Restaurants",
            "Quick Service",
            "Full Service",
            "Bars & Retail"
        ],
        "businessSize": "Small, Medium, Large",
        "posType": "iOS",
        "softwareType": "Cloud/SaaS",
        "freeTrial": "Demo Only",
        "merchantService": "In-House or Bring Your Own",
        "pricingModel": "Monthly Payment, Contract",
        "priceRange": ""
    },
    {
        "id": "9fdadf02",
        "productId": "c4304593",
        "productName": "Clover (Flex)",
        "bestFor": [
            "Small Business",
            "Retail",
            "Quick Service"
        ],
        "businessSize": "Small, Medium",
        "posType": "Android",
        "softwareType": "Cloud/SaaS",
        "freeTrial": "Yes",
        "merchantService": "In-House or Bring Your Own",
        "pricingModel": "Monthly Payment, Contract",
        "priceRange": ""
    },
    {
        "id": "fa233e08",
        "productId": "0fadfc8f",
        "productName": "Clover Duo",
        "bestFor": [
            "Restaurants",
            "Quick Service",
            "Full Service",
            "Retail",
            "Small Business"
        ],
        "businessSize": "Small, Medium",
        "posType": "Android",
        "softwareType": "Cloud/SaaS",
        "freeTrial": "Yes",
        "merchantService": "In-House or Bring Your Own",
        "pricingModel": "Monthly Payment, Contract",
        "priceRange": ""
    },
    {
        "id": "11b64961",
        "productId": "f32ba2b0",
        "productName": "Exatouch",
        "bestFor": [
            "Quick Service",
            "Retail",
            "Small Business",
            "Liqour Stores"
        ],
        "businessSize": "Small",
        "posType": "Windows",
        "softwareType": "Cloud",
        "freeTrial": "Yes",
        "merchantService": "In-House",
        "pricingModel": "Monthly Payment, No Contract",
        "priceRange": ""
    },
    {
        "id": "11b64961",
        "productId": "f9e0ef04",
        "productName": "Simphony",
        "bestFor": [
            "Restaurants",
            "Quick Service",
            "Bars",
            "Retail"
        ],
        "businessSize": "Medium, Large",
        "posType": "Windows",
        "softwareType": "Cloud/SaaS, On Premise (Windows)",
        "freeTrial": "Demo Only",
        "merchantService": "Bring Your Own",
        "pricingModel": "Monthly Payment, Annual Subscription, Contract",
        "priceRange": ""
    },
    {
        "id": "13a7bace",
        "productId": "8a013776",
        "productName": "Brink (Par)",
        "bestFor": [
            "Restaurants",
            "Bar",
            "Quick Service"
        ],
        "businessSize": "Small, Medium, Large",
        "posType": "Windows",
        "softwareType": "Cloud/SaaS",
        "freeTrial": "Demo Only",
        "merchantService": "Bring Your Own",
        "pricingModel": "Monthly Payment",
        "priceRange": ""
    },
    {
        "id": "262d5dff",
        "productId": "3f1943c6",
        "productName": "Ovvi",
        "bestFor": [
            "Restaurants",
            "Quick Service"
        ],
        "businessSize": "Small, Medium",
        "posType": "Android",
        "softwareType": "Cloud/SaaS",
        "freeTrial": "Yes",
        "merchantService": "Bring Your Own",
        "pricingModel": "Monthly Payment",
        "priceRange": ""
    },
    {
        "id": "3f2aa46a",
        "productId": "587824fd",
        "productName": "Aldelo",
        "bestFor": [
            "Restaurants",
            "Quick Service",
            "Full Service",
            "Bars"
        ],
        "businessSize": "Small, Medium, Large",
        "posType": "Android, iOS, Windows",
        "softwareType": "Cloud/SaaS",
        "freeTrial": "Yes",
        "merchantService": "In-House or Bring Your Own",
        "pricingModel": "Monthly Payment",
        "priceRange": ""
    },
    {
        "id": "add4ba7c",
        "productId": "f0ef18a8",
        "productName": "Lightspeed",
        "bestFor": [
            "Retail",
            "Small Business",
            "Ecommerce",
            "Liqour Stores"
        ],
        "businessSize": "Small, Medium, Large",
        "posType": "Android, iOS",
        "softwareType": "Cloud/SaaS, On Premise (Mac)",
        "freeTrial": "Yes",
        "merchantService": "In-House or Bring Your Own",
        "pricingModel": "Monthly Payment, Annual Subscription, Contract",
        "priceRange": ""
    },
    {
        "id": "7efa3a211",
        "productId": "4a659923",
        "productName": "Aloha",
        "bestFor": [
            "Restaurants",
            "Quick Service",
            "Full Service",
            "Bars"
        ],
        "businessSize": "Medium, Large",
        "posType": "Cloud, Windows",
        "softwareType": "Cloud/SaaS, On Premise (Windows)",
        "freeTrial": "Demo Only",
        "merchantService": "In-House or Bring Your Own",
        "pricingModel": "Monthly Payment, Contract",
        "priceRange": ""
    },
    {
        "id": "2eeef06e",
        "productId": "20621691",
        "productName": "Upserve",
        "bestFor": [
            "Restaurants",
            "Quick Service",
            "Full Service",
            "Bars"
        ],
        "businessSize": "Small, Medium",
        "posType": "Android, iPad POS",
        "softwareType": "Cloud/SaaS",
        "freeTrial": "Demo Only",
        "merchantService": "In-House Only",
        "pricingModel": "Monthly Payment, Contract",
        "priceRange": ""
    },
    {
        "id": "0d72ff42",
        "productId": "8fdf75eb",
        "productName": "Toast",
        "bestFor": [
            "Restaurants",
            "Quick Service",
            "Full Service"
        ],
        "businessSize": "Small, Medium",
        "posType": "Android",
        "softwareType": "Cloud/SaaS",
        "freeTrial": "Demo Only",
        "merchantService": "In-House Only",
        "pricingModel": "Monthly Payment, Contract",
        "priceRange": ""
    }
]